ecl/__init__.py
ecl/bin.py
ecl/ecl_type.py
ecl/ecl_util.py
ecl/version.py
ecl/.include/ert/ecl/EclFilename.hpp
ecl/.include/ert/ecl/EclKW.hpp
ecl/.include/ert/ecl/FortIO.hpp
ecl/.include/ert/ecl/ecl_box.hpp
ecl/.include/ert/ecl/ecl_coarse_cell.h
ecl/.include/ert/ecl/ecl_coarse_cell.hpp
ecl/.include/ert/ecl/ecl_endian_flip.h
ecl/.include/ert/ecl/ecl_endian_flip.hpp
ecl/.include/ert/ecl/ecl_file.h
ecl/.include/ert/ecl/ecl_file.hpp
ecl/.include/ert/ecl/ecl_file_kw.h
ecl/.include/ert/ecl/ecl_file_kw.hpp
ecl/.include/ert/ecl/ecl_file_view.h
ecl/.include/ert/ecl/ecl_file_view.hpp
ecl/.include/ert/ecl/ecl_grav.h
ecl/.include/ert/ecl/ecl_grav.hpp
ecl/.include/ert/ecl/ecl_grav_common.h
ecl/.include/ert/ecl/ecl_grav_common.hpp
ecl/.include/ert/ecl/ecl_grid.h
ecl/.include/ert/ecl/ecl_grid.hpp
ecl/.include/ert/ecl/ecl_grid_dims.h
ecl/.include/ert/ecl/ecl_grid_dims.hpp
ecl/.include/ert/ecl/ecl_init_file.h
ecl/.include/ert/ecl/ecl_init_file.hpp
ecl/.include/ert/ecl/ecl_io_config.h
ecl/.include/ert/ecl/ecl_io_config.hpp
ecl/.include/ert/ecl/ecl_kw.h
ecl/.include/ert/ecl/ecl_kw.hpp
ecl/.include/ert/ecl/ecl_kw_grdecl.h
ecl/.include/ert/ecl/ecl_kw_grdecl.hpp
ecl/.include/ert/ecl/ecl_kw_magic.h
ecl/.include/ert/ecl/ecl_kw_magic.hpp
ecl/.include/ert/ecl/ecl_nnc_data.h
ecl/.include/ert/ecl/ecl_nnc_data.hpp
ecl/.include/ert/ecl/ecl_nnc_export.h
ecl/.include/ert/ecl/ecl_nnc_export.hpp
ecl/.include/ert/ecl/ecl_nnc_geometry.h
ecl/.include/ert/ecl/ecl_nnc_geometry.hpp
ecl/.include/ert/ecl/ecl_region.h
ecl/.include/ert/ecl/ecl_region.hpp
ecl/.include/ert/ecl/ecl_rft_cell.h
ecl/.include/ert/ecl/ecl_rft_cell.hpp
ecl/.include/ert/ecl/ecl_rft_file.h
ecl/.include/ert/ecl/ecl_rft_file.hpp
ecl/.include/ert/ecl/ecl_rft_node.h
ecl/.include/ert/ecl/ecl_rft_node.hpp
ecl/.include/ert/ecl/ecl_rst_file.h
ecl/.include/ert/ecl/ecl_rst_file.hpp
ecl/.include/ert/ecl/ecl_rsthead.h
ecl/.include/ert/ecl/ecl_rsthead.hpp
ecl/.include/ert/ecl/ecl_smspec.h
ecl/.include/ert/ecl/ecl_smspec.hpp
ecl-2.14.5.dist-info/COPYING
ecl-2.14.5.dist-info/LICENSE
ecl-2.14.5.dist-info/METADATA
ecl-2.14.5.dist-info/WHEEL
ecl-2.14.5.dist-info/top_level.txt
ecl-2.14.5.dist-info/RECORD
